openlxp_P1_notification/__init__.py
openlxp_P1_notification/admin.py
openlxp_P1_notification/apps.py
openlxp_P1_notification/middleware.py
openlxp_P1_notification/models.py
openlxp_P1_notification/serializer.py
openlxp_P1_notification/urls.py
openlxp_P1_notification/views.py
openlxp_P1_notification/management/__init__.py
openlxp_P1_notification/management/commands/__init__.py
openlxp_P1_notification/management/commands/load_templates.py
openlxp_P1_notification/management/commands/trigger_status_update.py
openlxp_P1_notification/management/commands/trigger_subscribed_list_update.py
openlxp_P1_notification/management/utils/__init__.py
openlxp_P1_notification/management/utils/p1ps_configuration.py
openlxp_P1_notification/management/utils/p1ps_requests.py
openlxp_P1_notification/migrations/0001_initial.py
openlxp_P1_notification/migrations/0002_rename_template_body_template_message.py
openlxp_P1_notification/migrations/0003_auto_20240515_1827.py
openlxp_P1_notification/migrations/__init__.py
openlxp_P1_notification/tests/__init__.py
openlxp_P1_notification_project/__init__.py
openlxp_P1_notification_project/asgi.py
openlxp_P1_notification_project/settings.py
openlxp_P1_notification_project/urls.py
openlxp_P1_notification_project/wsgi.py
openlxp_P1_notification-0.0.18.dist-info/METADATA
openlxp_P1_notification-0.0.18.dist-info/WHEEL
openlxp_P1_notification-0.0.18.dist-info/top_level.txt
openlxp_P1_notification-0.0.18.dist-info/RECORD
